sa2schema/__init__.py
sa2schema/annotations.py
sa2schema/attribute_info.py
sa2schema/compat.py
sa2schema/defs.py
sa2schema/filter.py
sa2schema/property.py
sa2schema/sa_extract_info.py
sa2schema/to/__init__.py
sa2schema/to/pydantic/__init__.py
sa2schema/to/pydantic/annotations.py
sa2schema/to/pydantic/base_model.py
sa2schema/to/pydantic/base_model_recursion.py
sa2schema/to/pydantic/getter_dict.py
sa2schema/to/pydantic/models.py
sa2schema/to/pydantic/sa_model.py
sa2schema/to/pydantic/sa_pluck.py
sa2schema/to/pydantic/schema_tools.py
sa2schema/util.py
sa2schema-0.1.0b2.dist-info/WHEEL
sa2schema-0.1.0b2.dist-info/METADATA
sa2schema-0.1.0b2.dist-info/RECORD
